cosbot/__init__.py
cosbot/__main__.py
cosbot/src/__init__.py
cosbot/src/app/__init__.py
cosbot/src/app/app.py
cosbot/src/app/app_command.py
cosbot/src/app/app_connect.py
cosbot/src/app/app_search.py
cosbot/src/base/__init__.py
cosbot/src/base/argv.py
cosbot/src/base/cli_exec.py
cosbot/src/base/click.py
cosbot/src/base/dataset.py
cosbot/src/base/exceptions.py
cosbot/src/feature/__init__.py
cosbot/src/feature/methods.py
cosbot/src/feature/methods_app.py
cosbot/src/feature/methods_cli.py
cosbot/src/rest/__init__.py
cosbot/src/rest/bot_rest_api.py
cosbot/src/rest/bot_rest_api_methods.py
cosbot/src/texts/__init__.py
cosbot/src/texts/localization.py
cosbot/src/texts/texts.py
cosbot/src/texts/texts_error.py
cosbot/src/texts/texts_prompt.py
cosbot/src/websocket/__init__.py
cosbot/src/websocket/bot_received.py
cosbot/src/websocket/bot_reconnect.py
cosbot/src/websocket/bot_websocket.py
cosbot-0.0.16.dist-info/METADATA
cosbot-0.0.16.dist-info/WHEEL
cosbot-0.0.16.dist-info/entry_points.txt
cosbot-0.0.16.dist-info/top_level.txt
cosbot-0.0.16.dist-info/RECORD
