Metadata-Version: 2.1
Name: cosbot
Version: 0.0.16
Summary: An application that simplifies the life of an application developer for the Aurora OS.
Home-page: https://aurora-cos.keygenqt.com/cosbot/
Author: Vitaliy Zarubin
Author-email: keygenqt@gmail.com
Requires-Python: >=3.8.10
Requires-Dist: Telethon>=1.38.1
Requires-Dist: setuptools>=75.6.0
Requires-Dist: websocket-client>=1.8.0
Requires-Dist: requests>=2.32.3
Requires-Dist: aurora-cli>=3.2.10
Requires-Dist: beautifulsoup4>=4.12.3
Requires-Dist: click>=8.1.7
